robustgmm/__init__.py
robustgmm/generator.py
robustgmm/robustgmm.py
robustgmm-1.0.2.dist-info/METADATA
robustgmm-1.0.2.dist-info/WHEEL
robustgmm-1.0.2.dist-info/top_level.txt
robustgmm-1.0.2.dist-info/RECORD
