Metadata-Version: 2.1
Name: robustgmm
Version: 1.0.2
Summary: A robust EM clustering algorithm for Gaussian mixture models
Home-page: https://github.com/HongJea-Park/robust_EM_for_gmm.git
Author: HongJea Park
Author-email: hongjea.park@gmail.com
License: UNKNOWN
Platform: UNKNOWN
Requires-Python: >=3.6
Requires-Dist: numpy (>=1.17.1)
Requires-Dist: scipy (>=1.3.1)
Provides-Extra: all_extras
Requires-Dist: scikit-learn (>=0.2.0) ; extra == 'all_extras'
Requires-Dist: matplotlib (>=3.1.1) ; extra == 'all_extras'
Provides-Extra: dev
Requires-Dist: scikit-learn (>=0.2.0) ; extra == 'dev'
Requires-Dist: matplotlib (>=3.1.1) ; extra == 'dev'
Provides-Extra: test
Requires-Dist: scikit-learn (>=0.2.0) ; extra == 'test'
Requires-Dist: matplotlib (>=3.1.1) ; extra == 'test'
